CHANGES.rst
DEVELOP.rst
MANIFEST.in
README.rst
pyproject.toml
setup.cfg
setup.py
docs/LICENSE-GPL.rst
src/collective/__init__.py
src/collective.collectionfilter.egg-info/PKG-INFO
src/collective.collectionfilter.egg-info/SOURCES.txt
src/collective.collectionfilter.egg-info/dependency_links.txt
src/collective.collectionfilter.egg-info/entry_points.txt
src/collective.collectionfilter.egg-info/namespace_packages.txt
src/collective.collectionfilter.egg-info/not-zip-safe
src/collective.collectionfilter.egg-info/requires.txt
src/collective.collectionfilter.egg-info/top_level.txt
src/collective/collectionfilter/__init__.py
src/collective/collectionfilter/baseviews.py
src/collective/collectionfilter/configure.zcml
src/collective/collectionfilter/contentfilter.py
src/collective/collectionfilter/filteritems.py
src/collective/collectionfilter/interfaces.py
src/collective/collectionfilter/query.py
src/collective/collectionfilter/setuphandlers.py
src/collective/collectionfilter/testing.py
src/collective/collectionfilter/upgrades.py
src/collective/collectionfilter/upgrades.zcml
src/collective/collectionfilter/utils.py
src/collective/collectionfilter/validator.py
src/collective/collectionfilter/vocabularies.py
src/collective/collectionfilter/locales/collective.collectionfilter.pot
src/collective/collectionfilter/locales/plone.pot
src/collective/collectionfilter/locales/de-ch/LC_MESSAGES/collective.collectionfilter.po
src/collective/collectionfilter/locales/de-ch/LC_MESSAGES/plone.po
src/collective/collectionfilter/locales/de/LC_MESSAGES/collective.collectionfilter.po
src/collective/collectionfilter/locales/de/LC_MESSAGES/plone.po
src/collective/collectionfilter/locales/es/LC_MESSAGES/collective.collectionfilter.po
src/collective/collectionfilter/locales/es/LC_MESSAGES/plone.po
src/collective/collectionfilter/locales/eu/LC_MESSAGES/collective.collectionfilter.po
src/collective/collectionfilter/locales/eu/LC_MESSAGES/plone.po
src/collective/collectionfilter/locales/fr/LC_MESSAGES/collective.collectionfilter.po
src/collective/collectionfilter/locales/fr/LC_MESSAGES/plone.po
src/collective/collectionfilter/locales/nl/LC_MESSAGES/collective.collectionfilter.po
src/collective/collectionfilter/locales/nl/LC_MESSAGES/plone.po
src/collective/collectionfilter/locales/no/LC_MESSAGES/collective.collectionfilter.po
src/collective/collectionfilter/locales/no/LC_MESSAGES/plone.po
src/collective/collectionfilter/portlets/__init__.py
