Metadata-Version: 2.4
Name: collective.collectionfilter
Version: 5.3.1
Summary: Plone addon for filtering collection results.
Home-page: http://github.com/collective/collective.collectionfilter
Author: Johannes Raggam
Author-email: thetetet@gmail.com
License: GPL
Keywords: plone collection filter faceted tagcloud tags
Classifier: Development Status :: 5 - Production/Stable
Classifier: Framework :: Plone
Classifier: Framework :: Plone :: 6.0
Classifier: Framework :: Plone :: Addon
Classifier: License :: OSI Approved :: GNU General Public License v2 (GPLv2)
Classifier: Programming Language :: Python
Classifier: Programming Language :: Python :: 3.8
Classifier: Programming Language :: Python :: 3.9
Classifier: Programming Language :: Python :: 3.10
Classifier: Programming Language :: Python :: 3.11
Classifier: Topic :: Software Development :: Libraries :: Python Modules
Requires-Python: >=3.8
Requires-Dist: setuptools
Requires-Dist: plone.api>=2.0.0
Requires-Dist: plone.app.contenttypes
Requires-Dist: plone.app.event
Requires-Dist: plone.app.querystring
Requires-Dist: plone.app.uuid
Requires-Dist: plone.app.vocabularies
Requires-Dist: plone.app.z3cform
Requires-Dist: plone.autoform
Requires-Dist: plone.base
Requires-Dist: plone.dexterity
Requires-Dist: plone.i18n
Requires-Dist: plone.memoize
Requires-Dist: plone.portlets
Requires-Dist: plone.supermodel
Requires-Dist: plone.uuid
Requires-Dist: z3c.form
Requires-Dist: Products.CMFCore
Requires-Dist: Products.CMFPlone>=6.0
Provides-Extra: mosaic
Requires-Dist: plone.app.mosaic>=3.0.0; extra == "mosaic"
Provides-Extra: geolocation
Requires-Dist: collective.geolocationbehavior>=1.7.2; extra == "geolocation"
Requires-Dist: plone.formwidget.geolocation>=3.0.0; extra == "geolocation"
Provides-Extra: test
Requires-Dist: plone.app.mosaic; extra == "test"
Requires-Dist: plone.browserlayer; extra == "test"
Requires-Dist: plone.testing; extra == "test"
Requires-Dist: robotsuite; extra == "test"
Requires-Dist: collective.geolocationbehavior; extra == "test"
Requires-Dist: plone.app.testing[robot]; extra == "test"
Requires-Dist: plone.app.robotframework; extra == "test"
Requires-Dist: plone.app.contenttypes; extra == "test"
Requires-Dist: plone.app.portlets; extra == "test"
Requires-Dist: plone.app.textfield; extra == "test"
Requires-Dist: plone.app.discussion; extra == "test"
Requires-Dist: plone.tiles; extra == "test"
Dynamic: author
Dynamic: author-email
Dynamic: classifier
Dynamic: description
Dynamic: home-page
Dynamic: keywords
Dynamic: license
Dynamic: provides-extra
Dynamic: requires-dist
Dynamic: requires-python
Dynamic: summary
